handlers/__init__.py
handlers/time_handlers.py
mongo_pickle-0.1.5.dist-info/DESCRIPTION.rst
mongo_pickle-0.1.5.dist-info/METADATA
mongo_pickle-0.1.5.dist-info/RECORD
mongo_pickle-0.1.5.dist-info/WHEEL
mongo_pickle-0.1.5.dist-info/metadata.json
mongo_pickle-0.1.5.dist-info/top_level.txt
