Metadata-Version: 2.0
Name: mongo-pickle
Version: 0.1.5
Summary: Schema-less Pythonic Mongo ORM
Home-page: UNKNOWN
Author: 111yoav
Author-email: 111yoav@gmail.com
License: MIT
Platform: UNKNOWN
